pydbops/UserDefinedExceptions.py
pydbops/__init__.py
pydbops/database.py
pydbops/pydbops.py
pydbops/tables.py
pydbops-0.0.6.dist-info/LICENSE
pydbops-0.0.6.dist-info/METADATA
pydbops-0.0.6.dist-info/WHEEL
pydbops-0.0.6.dist-info/top_level.txt
pydbops-0.0.6.dist-info/RECORD
