Metadata-Version: 2.1
Name: pydbops
Version: 0.0.6
Summary: Simplifies the database operations.
Home-page: https://github.com/NotShrirang/pydbops
Author: Shrirang Mahajan
Author-email: shrirangmahajan123@gmail.com
Project-URL: Bug Tracker, https://github.com/NotShrirang/pydbops
Classifier: Programming Language :: Python :: 3
Classifier: License :: OSI Approved :: MIT License
Classifier: Operating System :: OS Independent
Requires-Python: >=3.6
License-File: LICENSE
